MANIFEST.in
README.md
setup.cfg
setup.py
confluence/__init__.py
confluence/confluence.py
confluence/version.py
confluence.egg-info/PKG-INFO
confluence.egg-info/SOURCES.txt
confluence.egg-info/dependency_links.txt
confluence.egg-info/not-zip-safe
confluence.egg-info/top_level.txt