Metadata-Version: 1.0
Name: confluence
Version: 0.1
Summary: A Python API to Confluence
Home-page: https://bitbucket.org/phoebian/confluence
Author: Sorin Sbarnea
Author-email: sorin.sbarnea@gmail.com
License: Python
Download-URL: https://bitbucket.org/phoebian/confluence/downloads
Keywords: confluence,atlassian
Platform: any
Classifier: Programming Language :: Python
Classifier: Programming Language :: Python :: 2.5
Classifier: Programming Language :: Python :: 2.6
Classifier: Programming Language :: Python :: 2.7
Classifier: Programming Language :: Python :: 3
Classifier: Development Status :: 4 - Beta
Classifier: Environment :: Other Environment
Classifier: Intended Audience :: Developers
Classifier: License :: OSI Approved :: BSD License
Classifier: Operating System :: OS Independent
Classifier: Topic :: Software Development :: Libraries :: Python Modules
Classifier: Topic :: Internet
